{"_version":1,"_url":"https://bip.katowice.eu/SiteAssets/Lists/Dokumenty/Uprawnienia/Sesja%203,%20Glosowanie%204,%20Data%2029.05.2024%2011.30.32.pdf","topic":"8. Rozpatrzenie projektu uchwały w sprawie przyjęcia sprawozdania z realizacji w 2023 r. „Programu gospodarowania mieszkaniowym zasobem miasta Katowice na lata 2021-2025” 4 oraz \"Zasad wynajmowania lokali wchodzących w skład mieszkaniowego zasobu miasta Katowice\" (DS-5/24).","counts":{"za":24,"przeciw":0,"wstrzymal_sie":1,"brak_glosu":0,"nieobecni":1},"named_votes":{"za":["Beata Bala","Krzysztof Pieczyński","Patryk Białas","Maciej Biskupski","Borys Pronobis","Łukasz Borkowski","Maria Ryś","Elżbieta Grodzka-Łopuszyńska","Ewa Sadkowska","Jacek Kalisz","Mariusz Skiba","Dawid Kamiński","Adam Skowron","Krzysztof Kraus","Magdalena Skwarek","Adam Lejman-Gąska","Damian Stępień","Urszula Machowska","Adam Szymczyk","Barbara Mańdok","Tomasz Maśnica","Andrzej Warmuz","Krystyna Panek","Magdalena Wieczorek"],"przeciw":[],"wstrzymal_sie":["Piotr Trząski"],"brak_glosu":[],"nieobecni":["Barbara Wnęk-Gabor"]}}